{
  "major": "History of Art and Visual Culture Minor",
  "from": {
    "id": 113,
    "code": "DAC     ",
    "isCommunityCollege": true,
    "category": "CCC",
    "termType": "Quarter",
    "names": [
      {
        "name": "De Anza College",
        "hasDepartments": true,
        "fromYear": 0,
        "hideInList": false
      }
    ],
    "termTypeAcademicYears": [
      {
        "termType": "Quarter",
        "fromYear": 1980
      }
    ]
  },
  "to": {
    "id": 132,
    "code": "UCSC    ",
    "isCommunityCollege": false,
    "category": "UC",
    "termType": "Quarter",
    "names": [
      {
        "name": "University of California, Santa Cruz",
        "hasDepartments": true,
        "fromYear": 0,
        "hideInList": false
      }
    ],
    "termTypeAcademicYears": [
      {
        "termType": "Quarter",
        "fromYear": 1980
      }
    ]
  },
  "agreements": [
    {
      "target": {
        "courseIdentifierParentId": 307065,
        "courseTitle": "Colonial Histories and Legacies: Africa, Oceania, and the Indigenous Americas",
        "courseNumber": "80",
        "prefix": "HAVC",
        "prefixParentId": 8194,
        "prefixDescription": "History of Art and Visual Culture",
        "departmentParentId": 7058,
        "department": "History of Art and Visual Culture",
        "begin": "F2010",
        "end": "",
        "minUnits": 5,
        "maxUnits": 5
      },
      "courses": [
        {
          "group": "And",
          "classes": [
            {
              "visibleCrossListedCourses": [
                {
                  "id": "3fbc16a0-f6b4-4696-afc1-926960491a80",
                  "publishedCourseIdentifierYearTermId": null,
                  "courseIdentifierParentId": 296555,
                  "courseTitle": "History of Art: Arts of Africa, Oceania and Native North America",
                  "courseNumber": "2J",
                  "prefix": "ARTS",
                  "prefixParentId": 4538,
                  "prefixDescription": "Arts",
                  "departmentParentId": 1240,
                  "department": "Arts",
                  "begin": "F2021",
                  "end": "",
                  "minUnits": 4,
                  "maxUnits": 4
                }
              ],
              "requisites": [],
              "attributes": [],
              "courseIdentifierParentId": 296554,
              "courseTitle": "History of Art: Arts of Africa, Oceania and Native North America",
              "courseNumber": "22",
              "prefix": "INTL",
              "prefixParentId": 767,
              "prefixDescription": "International Studies",
              "departmentParentId": 7709,
              "department": "International Studies",
              "begin": "F2021",
              "end": "",
              "minUnits": 4,
              "maxUnits": 4,
              "publishedCourseIdentifierYearTermId": null,
              "position": 0,
              "type": "Course"
            }
          ]
        },
        {
          "group": "And",
          "classes": [
            {
              "visibleCrossListedCourses": [
                {
                  "id": "55de82b0-e8c4-4ed7-aba9-a2cd74f1c981",
                  "publishedCourseIdentifierYearTermId": null,
                  "courseIdentifierParentId": 296554,
                  "courseTitle": "History of Art: Arts of Africa, Oceania and Native North America",
                  "courseNumber": "22",
                  "prefix": "INTL",
                  "prefixParentId": 767,
                  "prefixDescription": "International Studies",
                  "departmentParentId": 7709,
                  "department": "International Studies",
                  "begin": "F2021",
                  "end": "",
                  "minUnits": 4,
                  "maxUnits": 4
                }
              ],
              "requisites": [],
              "attributes": [],
              "courseIdentifierParentId": 296555,
              "courseTitle": "History of Art: Arts of Africa, Oceania and Native North America",
              "courseNumber": "2J",
              "prefix": "ARTS",
              "prefixParentId": 4538,
              "prefixDescription": "Arts",
              "departmentParentId": 1240,
              "department": "Arts",
              "begin": "F2021",
              "end": "",
              "minUnits": 4,
              "maxUnits": 4,
              "publishedCourseIdentifierYearTermId": null,
              "position": 0,
              "type": "Course"
            }
          ]
        }
      ]
    },
    {
      "courses": [
        {
          "group": "And",
          "classes": [
            {
              "visibleCrossListedCourses": [
                {
                  "id": "cf2aa504-2045-4bb2-9ed5-2b1ce7fa52d2",
                  "publishedCourseIdentifierYearTermId": null,
                  "courseIdentifierParentId": 353552,
                  "courseTitle": "History of Art: Arts of Asia",
                  "courseNumber": "40",
                  "prefix": "ASAM",
                  "prefixParentId": 16555,
                  "prefixDescription": "Asian American and Asian Studies",
                  "departmentParentId": 13706,
                  "department": "Asian American and Asian Studies",
                  "begin": "F2021",
                  "end": "",
                  "minUnits": 4,
                  "maxUnits": 4
                }
              ],
              "requisites": [],
              "attributes": [],
              "courseIdentifierParentId": 353553,
              "courseTitle": "History of Art: Arts of Asia",
              "courseNumber": "2G",
              "prefix": "ARTS",
              "prefixParentId": 4538,
              "prefixDescription": "Arts",
              "departmentParentId": 1240,
              "department": "Arts",
              "begin": "F2016",
              "end": "",
              "minUnits": 4,
              "maxUnits": 4,
              "publishedCourseIdentifierYearTermId": null,
              "position": 0,
              "type": "Course"
            }
          ]
        },
        {
          "group": "And",
          "classes": [
            {
              "visibleCrossListedCourses": [
                {
                  "id": "4a8aeeed-6308-4660-a954-54988a9bdec5",
                  "publishedCourseIdentifierYearTermId": null,
                  "courseIdentifierParentId": 353553,
                  "courseTitle": "History of Art: Arts of Asia",
                  "courseNumber": "2G",
                  "prefix": "ARTS",
                  "prefixParentId": 4538,
                  "prefixDescription": "Arts",
                  "departmentParentId": 1240,
                  "department": "Arts",
                  "begin": "F2016",
                  "end": "",
                  "minUnits": 4,
                  "maxUnits": 4
                }
              ],
              "requisites": [],
              "attributes": [],
              "courseIdentifierParentId": 353552,
              "courseTitle": "History of Art: Arts of Asia",
              "courseNumber": "40",
              "prefix": "ASAM",
              "prefixParentId": 16555,
              "prefixDescription": "Asian American and Asian Studies",
              "departmentParentId": 13706,
              "department": "Asian American and Asian Studies",
              "begin": "F2021",
              "end": "",
              "minUnits": 4,
              "maxUnits": 4,
              "publishedCourseIdentifierYearTermId": null,
              "position": 0,
              "type": "Course"
            }
          ]
        }
      ]
    },
    {
      "courses": [
        {
          "group": "And",
          "classes": [
            {
              "visibleCrossListedCourses": [
                {
                  "id": "04b642e0-b74e-4be2-968e-9badab679f1b",
                  "publishedCourseIdentifierYearTermId": null,
                  "courseIdentifierParentId": 253928,
                  "courseTitle": "History of Art: Multicultural Arts in the United States",
                  "courseNumber": "2F",
                  "prefix": "ARTS",
                  "prefixParentId": 4538,
                  "prefixDescription": "Arts",
                  "departmentParentId": 1240,
                  "department": "Arts",
                  "begin": "F2021",
                  "end": "",
                  "minUnits": 4,
                  "maxUnits": 4
                }
              ],
              "requisites": [],
              "attributes": [],
              "courseIdentifierParentId": 253927,
              "courseTitle": "History of Art: Multicultural Arts in the United States",
              "courseNumber": "13",
              "prefix": "CETH",
              "prefixParentId": 16886,
              "prefixDescription": "Comparative Ethnic Studies",
              "departmentParentId": 13991,
              "department": "Comparative Ethnic Studies",
              "begin": "F2021",
              "end": "",
              "minUnits": 4,
              "maxUnits": 4,
              "publishedCourseIdentifierYearTermId": null,
              "position": 0,
              "type": "Course"
            }
          ]
        },
        {
          "group": "And",
          "classes": [
            {
              "visibleCrossListedCourses": [
                {
                  "id": "59771600-edfc-4993-ad4b-49738b27a824",
                  "publishedCourseIdentifierYearTermId": null,
                  "courseIdentifierParentId": 253927,
                  "courseTitle": "History of Art: Multicultural Arts in the United States",
                  "courseNumber": "13",
                  "prefix": "CETH",
                  "prefixParentId": 16886,
                  "prefixDescription": "Comparative Ethnic Studies",
                  "departmentParentId": 13991,
                  "department": "Comparative Ethnic Studies",
                  "begin": "F2021",
                  "end": "",
                  "minUnits": 4,
                  "maxUnits": 4
                }
              ],
              "requisites": [],
              "attributes": [],
              "courseIdentifierParentId": 253928,
              "courseTitle": "History of Art: Multicultural Arts in the United States",
              "courseNumber": "2F",
              "prefix": "ARTS",
              "prefixParentId": 4538,
              "prefixDescription": "Arts",
              "departmentParentId": 1240,
              "department": "Arts",
              "begin": "F2021",
              "end": "",
              "minUnits": 4,
              "maxUnits": 4,
              "publishedCourseIdentifierYearTermId": null,
              "position": 0,
              "type": "Course"
            }
          ]
        },
        {
          "group": "And",
          "classes": [
            {
              "visibleCrossListedCourses": [],
              "requisites": [],
              "attributes": [],
              "courseIdentifierParentId": 253849,
              "courseTitle": "History of Art: Europe During the Middle Ages and the Renaissance",
              "courseNumber": "2B",
              "prefix": "ARTS",
              "prefixParentId": 4538,
              "prefixDescription": "Arts",
              "departmentParentId": 1240,
              "department": "Arts",
              "begin": "F2016",
              "end": "",
              "minUnits": 4,
              "maxUnits": 4,
              "publishedCourseIdentifierYearTermId": null,
              "position": 0,
              "type": "Course"
            }
          ]
        },
        {
          "group": "And",
          "classes": [
            {
              "visibleCrossListedCourses": [],
              "requisites": [],
              "attributes": [],
              "courseIdentifierParentId": 289337,
              "courseTitle": "History of Art: Europe and the United States from Post-Impressionism to the Present",
              "courseNumber": "2D",
              "prefix": "ARTS",
              "prefixParentId": 4538,
              "prefixDescription": "Arts",
              "departmentParentId": 1240,
              "department": "Arts",
              "begin": "F2016",
              "end": "",
              "minUnits": 4,
              "maxUnits": 4,
              "publishedCourseIdentifierYearTermId": null,
              "position": 0,
              "type": "Course"
            }
          ]
        },
        {
          "group": "And",
          "classes": [
            {
              "visibleCrossListedCourses": [],
              "requisites": [],
              "attributes": [],
              "courseIdentifierParentId": 254925,
              "courseTitle": "Architecture Past and Present",
              "courseNumber": "1B",
              "prefix": "ARTS",
              "prefixParentId": 4538,
              "prefixDescription": "Arts",
              "departmentParentId": 1240,
              "department": "Arts",
              "begin": "F1995",
              "end": "",
              "minUnits": 4,
              "maxUnits": 4,
              "publishedCourseIdentifierYearTermId": null,
              "position": 0,
              "type": "Course"
            }
          ]
        },
        {
          "group": "And",
          "classes": [
            {
              "visibleCrossListedCourses": [],
              "requisites": [],
              "attributes": [],
              "courseIdentifierParentId": 281454,
              "courseTitle": "History of Art: Europe from the Baroque Period through Impressionism",
              "courseNumber": "2C",
              "prefix": "ARTS",
              "prefixParentId": 4538,
              "prefixDescription": "Arts",
              "departmentParentId": 1240,
              "department": "Arts",
              "begin": "F2016",
              "end": "",
              "minUnits": 4,
              "maxUnits": 4,
              "publishedCourseIdentifierYearTermId": null,
              "position": 0,
              "type": "Course"
            }
          ]
        }
      ]
    },
    {
      "courses": [
        {
          "group": "And",
          "classes": [
            {
              "visibleCrossListedCourses": [],
              "requisites": [],
              "attributes": [],
              "courseIdentifierParentId": 254867,
              "courseTitle": "History of Art: Europe from Prehistory through Early Christianity",
              "courseNumber": "2A",
              "prefix": "ARTS",
              "prefixParentId": 4538,
              "prefixDescription": "Arts",
              "departmentParentId": 1240,
              "department": "Arts",
              "begin": "F2016",
              "end": "",
              "minUnits": 4,
              "maxUnits": 4,
              "publishedCourseIdentifierYearTermId": null,
              "position": 0,
              "type": "Course"
            }
          ]
        }
      ]
    },
    {
      "courses": [
        {
          "group": "And",
          "classes": [
            {
              "visibleCrossListedCourses": [
                {
                  "id": "a5fd94a5-1603-4a19-98ca-dfa9a5ad69ba",
                  "publishedCourseIdentifierYearTermId": null,
                  "courseIdentifierParentId": 266302,
                  "courseTitle": "History of Art: Native Arts of Mesoamerica and the Andes",
                  "courseNumber": "21",
                  "prefix": "INTL",
                  "prefixParentId": 767,
                  "prefixDescription": "International Studies",
                  "departmentParentId": 7709,
                  "department": "International Studies",
                  "begin": "F2021",
                  "end": "",
                  "minUnits": 4,
                  "maxUnits": 4
                }
              ],
              "requisites": [],
              "attributes": [],
              "courseIdentifierParentId": 266303,
              "courseTitle": "History of Art: Native Arts of Mesoamerica and the Andes",
              "courseNumber": "2H",
              "prefix": "ARTS",
              "prefixParentId": 4538,
              "prefixDescription": "Arts",
              "departmentParentId": 1240,
              "department": "Arts",
              "begin": "F2016",
              "end": "",
              "minUnits": 4,
              "maxUnits": 4,
              "publishedCourseIdentifierYearTermId": null,
              "position": 0,
              "type": "Course"
            }
          ]
        },
        {
          "group": "And",
          "classes": [
            {
              "visibleCrossListedCourses": [
                {
                  "id": "283180f5-4d4e-49cf-a977-0665bb1b156d",
                  "publishedCourseIdentifierYearTermId": null,
                  "courseIdentifierParentId": 266303,
                  "courseTitle": "History of Art: Native Arts of Mesoamerica and the Andes",
                  "courseNumber": "2H",
                  "prefix": "ARTS",
                  "prefixParentId": 4538,
                  "prefixDescription": "Arts",
                  "departmentParentId": 1240,
                  "department": "Arts",
                  "begin": "F2016",
                  "end": "",
                  "minUnits": 4,
                  "maxUnits": 4
                }
              ],
              "requisites": [],
              "attributes": [],
              "courseIdentifierParentId": 266302,
              "courseTitle": "History of Art: Native Arts of Mesoamerica and the Andes",
              "courseNumber": "21",
              "prefix": "INTL",
              "prefixParentId": 767,
              "prefixDescription": "International Studies",
              "departmentParentId": 7709,
              "department": "International Studies",
              "begin": "F2021",
              "end": "",
              "minUnits": 4,
              "maxUnits": 4,
              "publishedCourseIdentifierYearTermId": null,
              "position": 0,
              "type": "Course"
            }
          ]
        },
        {
          "group": "And",
          "classes": [
            {
              "visibleCrossListedCourses": [],
              "requisites": [],
              "attributes": [],
              "courseIdentifierParentId": 253916,
              "courseTitle": "Survey of Native American Arts",
              "courseNumber": "13",
              "prefix": "NAIS",
              "prefixParentId": 16887,
              "prefixDescription": "Native American and Indigenous Studies",
              "departmentParentId": 13992,
              "department": "Native American and Indigenous Studies",
              "begin": "F2021",
              "end": "",
              "minUnits": 4,
              "maxUnits": 4,
              "publishedCourseIdentifierYearTermId": null,
              "position": 0,
              "type": "Course"
            }
          ]
        }
      ]
    }
  ],
  "groups": {
    "PREPARATION FOR THE MINOR": [
      {
        "instruction": {
          "type": "NFromArea",
          "amount": 3,
          "amountQuantifier": "None",
          "amountUnitType": "Course",
          "toAmountDeterminer": "None",
          "toAmount": 1,
          "areaType": "None",
          "id": "98e9b04b-3181-43b7-e1af-08db99b6efac",
          "selectionType": "Complete"
        },
        "sections": [
          [
            {
              "type": "Requirement",
              "requirement": {
                "name": "Asia and its Diaspora"
              },
              "requirementAttributes": [],
              "id": "5b4b5883-2e64-4246-8b1b-b9f06f478b08",
              "position": 0,
              "attributes": []
            },
            {
              "type": "Requirement",
              "requirement": {
                "name": "Oceania and its Diaspora"
              },
              "requirementAttributes": [],
              "id": "0d194e72-07cd-455c-9807-eeaf8e37882e",
              "position": 0,
              "attributes": []
            },
            {
              "type": "Requirement",
              "requirement": {
                "name": "Africa and its Diaspora"
              },
              "requirementAttributes": [],
              "id": "0b3b01b2-42c2-4c04-9e2b-62a9b089d012",
              "position": 0,
              "attributes": []
            },
            {
              "type": "Course",
              "course": {
                "courseIdentifierParentId": 307065,
                "courseTitle": "Colonial Histories and Legacies: Africa, Oceania, and the Indigenous Americas",
                "courseNumber": "80",
                "prefix": "HAVC",
                "prefixParentId": 8194,
                "prefixDescription": "History of Art and Visual Culture",
                "departmentParentId": 7058,
                "department": "History of Art and Visual Culture",
                "begin": "F2010",
                "end": "",
                "minUnits": 5,
                "maxUnits": 5
              },
              "visibleCrossListedCourses": [],
              "requisites": [],
              "courseAttributes": [
                {
                  "position": 0,
                  "content": "**REFER TO TOP OF AGREEMENT**"
                }
              ],
              "id": "fda43f5e-78e2-48f5-b4b8-44fddc6565a5",
              "position": 0,
              "attributes": []
            },
            {
              "type": "Requirement",
              "requirement": {
                "name": "Europe and the Americas"
              },
              "requirementAttributes": [],
              "id": "cf512937-274d-4e95-b91c-3d761efe1cd0",
              "position": 0,
              "attributes": []
            },
            {
              "type": "Requirement",
              "requirement": {
                "name": "Mediterranean"
              },
              "requirementAttributes": [],
              "id": "c7304771-70c2-487f-a276-c788a6e8b1e2",
              "position": 0,
              "attributes": []
            },
            {
              "type": "Requirement",
              "requirement": {
                "name": "Native Americas"
              },
              "requirementAttributes": [],
              "id": "63c2faff-9774-4791-aa2f-8a6e0ddfd0f1",
              "position": 0,
              "attributes": []
            }
          ]
        ]
      }
    ]
  }
}